kahn/__init__.py
kahn/cli.py
kahn/core.py
kahn/util.py
kahn-0.0.1.dist-info/LICENSE
kahn-0.0.1.dist-info/METADATA
kahn-0.0.1.dist-info/WHEEL
kahn-0.0.1.dist-info/entry_points.txt
kahn-0.0.1.dist-info/top_level.txt
kahn-0.0.1.dist-info/RECORD
