Metadata-Version: 2.1
Name: kahn
Version: 0.0.1
Summary: A light-weight and energy-efficient NMEA message broker
Home-page: https://github.com/maritime-labs/kahn
Download-URL: https://pypi.org/project/kahn/
Author: Andreas Motl
Author-email: andreas.motl@panodata.org
License: AGPL-3.0, EUPL-1.2
Keywords: message,broker,opencpn,signalk,openplotter,nmea,nmea-0183,sailing,sensor
Classifier: Programming Language :: Python
Classifier: Programming Language :: Python :: 3
Classifier: Programming Language :: Python :: 3.7
Classifier: Programming Language :: Python :: 3.8
Classifier: Programming Language :: Python :: 3.9
Classifier: Programming Language :: Python :: 3.10
Classifier: License :: OSI Approved :: GNU Affero General Public License v3
Classifier: License :: OSI Approved :: European Union Public Licence 1.2 (EUPL 1.2)
Classifier: Development Status :: 2 - Pre-Alpha
Classifier: Operating System :: POSIX :: Linux
Classifier: Operating System :: MacOS
Classifier: Natural Language :: English
Classifier: Intended Audience :: Customer Service
Classifier: Intended Audience :: Developers
Classifier: Intended Audience :: Education
Classifier: Intended Audience :: Information Technology
Classifier: Intended Audience :: Manufacturing
Classifier: Intended Audience :: Science/Research
Classifier: Intended Audience :: System Administrators
Classifier: Intended Audience :: Telecommunications Industry
Classifier: Topic :: Communications
Classifier: Topic :: Education :: Testing
Classifier: Topic :: Software Development :: Libraries
Classifier: Topic :: Scientific/Engineering
Classifier: Topic :: System :: Emulators
Classifier: Topic :: System :: Networking
Classifier: Topic :: Utilities
License-File: LICENSE
Requires-Dist: pyserial (<4)
Requires-Dist: pynmea2 (<2,>1)
Requires-Dist: click (<9)
Requires-Dist: importlib-metadata ; python_version <= "3.7"
Provides-Extra: test
Requires-Dist: pytest (<8) ; extra == 'test'
Requires-Dist: pytest-cov (<4) ; extra == 'test'
Requires-Dist: mock-serial (<1) ; extra == 'test'
